Metadata-Version: 2.1
Name: commit-helper-testing
Version: 3.4.8
Summary: A python program that helps you write commits following commit conventions
Home-page: https://github.com/alaxalves/commit-helper
Author: Andre de Sousa Costa Filho
Author-email: andre.filho001@outlook.com
License: GNU
Platform: UNKNOWN
Classifier: Development Status :: 5 - Production/Stable
Classifier: Intended Audience :: Developers
Classifier: Natural Language :: Portuguese
Classifier: License :: OSI Approved :: MIT License
Classifier: Operating System :: OS Independent
Classifier: Programming Language :: Python
Classifier: Programming Language :: Python :: 3.6
Classifier: Programming Language :: Python :: Implementation :: CPython
Classifier: Programming Language :: Python :: Implementation :: PyPy
Classifier: Topic :: Software Development :: Libraries :: Python Modules
Requires-Dist: argh (==0.26.2)
Requires-Dist: atomicwrites (==1.2.1)
Requires-Dist: attrs (==18.2.0)
Requires-Dist: certifi (==2018.11.29)
Requires-Dist: chardet (==3.0.4)
Requires-Dist: codacy-coverage (==1.3.11)
Requires-Dist: codeclimate-test-reporter (==0.2.3)
Requires-Dist: colorama (==0.4.1)
Requires-Dist: colored (==1.3.93)
Requires-Dist: coverage (==4.5.2)
Requires-Dist: docopt (==0.6.2)
Requires-Dist: idna (==2.8)
Requires-Dist: more-itertools (==4.3.0)
Requires-Dist: pathlib (==1.0.1)
Requires-Dist: pathtools (==0.1.2)
Requires-Dist: pip (==18.1)
Requires-Dist: pluggy (==0.8.0)
Requires-Dist: py (==1.7.0)
Requires-Dist: pycodestyle (==2.4.0)
Requires-Dist: pytest (==4.0.1)
Requires-Dist: pytest-cov (==2.6.0)
Requires-Dist: pytest-watch (==4.2.0)
Requires-Dist: PyYAML (==3.13)
Requires-Dist: requests (==2.21.0)
Requires-Dist: setuptools (==40.6.2)
Requires-Dist: six (==1.12.0)
Requires-Dist: urllib3 (==1.24.1)
Requires-Dist: watchdog (==0.9.0)
Requires-Dist: wheel (==0.32.2)
Requires-Dist: twine (==1.12.1)
